sisyphus1/rtl/register.v
module register(

    // Inputs
    input wire [4:0] rs1_addr,
    input wire [4:0] rs2_addr,
    input wire rw1,
    input wire [4:0] rw_addr,
    input wire [31:0] rw_data,

    // Outputs
    output reg [31:0] rs1_data,
    output reg [31:0] rs2_data,

    // Clock
    input wire clk
);

    // Storage
    reg [31:0] regs [31:0];

    // Reads: combinational, always live -- x0 forced to zero regardless of storage
    always @(*) begin
        rs1_data = (rs1_addr == 5'd0) ? 32'b0 : regs[rs1_addr];
        rs2_data = (rs2_addr == 5'd0) ? 32'b0 : regs[rs2_addr];
    end

    // Write: synchronous, commits only on the clock edge -- x0 is never written
    always @(posedge clk) begin
        if (rw1 && rw_addr != 5'd0) begin
            regs[rw_addr] <= rw_data;
        end
    end

endmodule

sisyphus1/tb/register_tb.v
module register_tb ();

    reg [4:0] rs1_addr;
    reg [4:0] rs2_addr;
    reg rw1;
    reg [4:0] rw_addr;
    reg [31:0] rw_data;
    reg clk;

    wire [31:0] rs1_data;
    wire [31:0] rs2_data;

    integer errors;
    integer total;
    integer i;
    integer seed;
    reg [4:0] rand_addr;
    reg [31:0] rand_data_old;
    reg [31:0] rand_data_new;

    register register_instance (
        .rs1_addr(rs1_addr),
        .rs2_addr(rs2_addr),
        .rw1(rw1),
        .rw_addr(rw_addr),
        .rw_data(rw_data),
        .rs1_data(rs1_data),
        .rs2_data(rs2_data),
        .clk(clk)
    );

    // Free-running clock: flips every 5 time units -> 10-unit period
    always #5 clk = ~clk;

    // Commits a write and waits for it to actually land before returning
    task write_reg;
        input [4:0] addr;
        input [31:0] data;
        begin
            rw_addr = addr;
            rw_data = data;
            rw1 = 1;
            @(posedge clk);
            #1;
            rw1 = 0;
            #1;
        end
    endtask

    initial begin
        $dumpfile("register_tb.vcd");
        $dumpvars(0, register_tb);

        clk = 0;
        rw1 = 0;
        errors = 0;
        total = 0;
        seed = 54321;

        // -------------------------------------------------------
        // test out x0
        // -------------------------------------------------------
        rs1_addr = 5'b0;
        #1;
        if (rs1_data == 32'b0) begin // first read is good
            rw1 = 1;
            rw_addr = 5'b0;
            rw_data = 32'b1;
            @(posedge clk); // wait for the write to actually commit
            #1;             // let the combinational read settle after the edge
            if (rs1_data == 32'b0) begin // write was correctly ignored
                $display("Passed the x0 test!");
            end
            else begin
                $display("Failed the x0 test on write-read");
            end
        end
        else begin
            $display("Failed x0 test: x0 not 0");
        end
        rw1 = 0;

        // -------------------------------------------------------
        // test write-then-read same cycle, ordinary registers
        // -------------------------------------------------------
        for (i = 0; i < 50; i = i + 1) begin
            total = total + 1;

            rand_addr = $random(seed);
            if (rand_addr == 5'd0) rand_addr = 5'd1; // x0 already covered above
            rand_data_old = $random(seed);
            rand_data_new = $random(seed);

            // get a known baseline value into the register first
            write_reg(rand_addr, rand_data_old);

            // read it -- should show the old value before any new write commits
            rs1_addr = rand_addr;
            #1;
            if (rs1_data !== rand_data_old) begin
                errors = errors + 1;
                $display("FAIL (pre-write): addr=%0d expected=%h got=%h", rand_addr, rand_data_old, rs1_data);
            end

            // now write a new value to the same address, same address still being read
            rw_addr = rand_addr;
            rw_data = rand_data_new;
            rw1 = 1;
            @(posedge clk);
            #1;
            rw1 = 0;

            // should show the new value immediately after the edge commits
            if (rs1_data !== rand_data_new) begin
                errors = errors + 1;
                $display("FAIL (post-write): addr=%0d expected=%h got=%h", rand_addr, rand_data_new, rs1_data);
            end
        end

        $display("write-then-read: %0d / %0d passed", total - errors, total);
        $finish;
    end

endmodule

sisyphus1/register_tb.vcd
$date
	Wed Aug  5 23:17:53 2026
$end
$version
	Icarus Verilog
$end
$timescale
	1s
$end
$scope module register_tb $end
$var wire 32 ! rs2_data [31:0] $end
$var wire 32 " rs1_data [31:0] $end
$var reg 1 # clk $end
$var reg 5 $ rand_addr [4:0] $end
$var reg 32 % rand_data_new [31:0] $end
$var reg 32 & rand_data_old [31:0] $end
$var reg 5 ' rs1_addr [4:0] $end
$var reg 5 ( rs2_addr [4:0] $end
$var reg 1 ) rw1 $end
$var reg 5 * rw_addr [4:0] $end
$var reg 32 + rw_data [31:0] $end
$var integer 32 , errors [31:0] $end
$var integer 32 - i [31:0] $end
$var integer 32 . seed [31:0] $end
$var integer 32 / total [31:0] $end
$scope module register_instance $end
$var wire 1 # clk $end
$var wire 5 0 rs1_addr [4:0] $end
$var wire 5 1 rs2_addr [4:0] $end
$var wire 1 ) rw1 $end
$var wire 5 2 rw_addr [4:0] $end
$var wire 32 3 rw_data [31:0] $end
$var reg 32 4 rs1_data [31:0] $end
$var reg 32 5 rs2_data [31:0] $end
$upscope $end
$scope task write_reg $end
$var reg 5 6 addr [4:0] $end
$var reg 32 7 data [31:0] $end
$upscope $end
$upscope $end
$enddefinitions $end
$comment Show the parameter values. $end
$dumpall
$end
#0
$dumpvars
bx 7
bx 6
bx 5
b0 4
bx 3
bx 2
bx 1
b0 0
b0 /
b1101010000110001 .
bx -
b0 ,
bx +
bx *
0)
bx (
b0 '
bx &
bx %
bx $
0#
b0 "
bx !
$end
#1
b1 +
b1 3
b0 *
b0 2
1)
#5
1#
#6
b101110110010011010000101011101 +
b101110110010011010000101011101 3
b11111 *
b11111 2
b101110110010011010000101011101 7
b11111 6
b1010100001101110101010110101000 %
b101110110010011010000101011101 &
b11111 $
b11010100001101110101001110111100 .
b1 /
b0 -
1)
#10
0#
#15
1#
#16
0)
#17
b101110110010011010000101011101 "
b101110110010011010000101011101 4
b11111 '
b11111 0
#18
1)
b1010100001101110101010110101000 +
b1010100001101110101010110101000 3
#20
0#
#25
b1010100001101110101010110101000 "
b1010100001101110101010110101000 4
1#
#26
b1010110000101100010000110101100 +
b1010110000101100010000110101100 3
b110 *
b110 2
b1010110000101100010000110101100 7
b110 6
b101110001100101010010101011100 %
b1010110000101100010000110101100 &
b110 $
b10101110001100101010001101100011 .
b10 /
b1 -
1)
#30
0#
#35
1#
#36
0)
#37
b1010110000101100010000110101100 "
b1010110000101100010000110101100 4
b110 '
b110 0
#38
1)
b101110001100101010010101011100 +
b101110001100101010010101011100 3
#40
0#
#45
b101110001100101010010101011100 "
b101110001100101010010101011100 4
1#
#46
b10111011011101001101110001110110 +
b10111011011101001101110001110110 3
b1000 *
b1000 2
b10111011011101001101110001110110 7
b1000 6
b11100110010101101011000011001100 %
b10111011011101001101110001110110 &
b1000 $
b1100110010101101010111001010110 .
b11 /
b10 -
1)
#50
0#
#55
1#
#56
0)
#57
b10111011011101001101110001110110 "
b10111011011101001101110001110110 4
b1000 '
b1000 0
#58
1)
b11100110010101101011000011001100 +
b11100110010101101011000011001100 3
#60
0#
#65
b11100110010101101011000011001100 "
b11100110010101101011000011001100 4
1#
#66
b101101110011101001111101011011 +
b101101110011101001111101011011 3
b10001 *
b10001 2
b101101110011101001111101011011 7
b10001 6
b11001010000010001011010010010100 %
b101101110011101001111101011011 &
b10001 $
b1001010000010001011001110000101 .
b100 /
b11 -
1)
#70
0#
#75
1#
#76
0)
#77
b101101110011101001111101011011 "
b101101110011101001111101011011 4
b10001 '
b10001 0
#78
1)
b11001010000010001011010010010100 +
b11001010000010001011010010010100 3
#80
0#
#85
b11001010000010001011010010010100 "
b11001010000010001011010010010100 4
1#
#86
b10011111110111010001111000111111 +
b10011111110111010001111000111111 3
b11011 *
b11011 2
b10011111110111010001111000111111 7
b11011 6
b1011010100101111110001110110101 %
b10011111110111010001111000111111 &
b11011 $
b11011010100101111110000010100000 .
b101 /
b100 -
1)
#90
0#
#95
1#
#96
0)
#97
b10011111110111010001111000111111 "
b10011111110111010001111000111111 4
b11011 '
b11011 0
#98
1)
b1011010100101111110001110110101 +
b1011010100101111110001110110101 3
#100
0#
#105
b1011010100101111110001110110101 "
b1011010100101111110001110110101 4
1#
#106
b111010110111011100100101110101 +
b111010110111011100100101110101 3
b101 *
b101 2
b111010110111011100100101110101 7
b101 6
b101110001001110100101101011100 %
b111010110111011100100101110101 &
b101 $
b10101110001001110100100100010111 .
b110 /
b101 -
1)
#110
0#
#115
1#
#116
0)
#117
b111010110111011100100101110101 "
b111010110111011100100101110101 4
b101 '
b101 0
#118
1)
b101110001001110100101101011100 +
b101110001001110100101101011100 3
#120
0#
#125
b101110001001110100101101011100 "
b101110001001110100101101011100 4
1#
#126
b100011111001000101111101000111 +
b100011111001000101111101000111 3
b11010 *
b11010 2
b100011111001000101111101000111 7
b11010 6
b10110011000011010110101001100110 %
b100011111001000101111101000111 &
b11010 $
b110011000011010110100100011010 .
b111 /
b110 -
1)
#130
0#
#135
1#
#136
0)
#137
b100011111001000101111101000111 "
b100011111001000101111101000111 4
b11010 '
b11010 0
#138
1)
b10110011000011010110101001100110 +
b10110011000011010110101001100110 3
#140
0#
#145
b10110011000011010110101001100110 "
b10110011000011010110101001100110 4
1#
#146
b11010100100010001110000010101001 +
b11010100100010001110000010101001 3
b10010 *
b10010 2
b11010100100010001110000010101001 7
b10010 6
b11111001010010011100000111 %
b11010100100010001110000010101001 &
b10010 $
b10000011111001010010010010011001 .
b1000 /
b111 -
1)
#150
0#
#155
1#
#156
0)
#157
b11010100100010001110000010101001 "
b11010100100010001110000010101001 4
b10010 '
b10010 0
#158
1)
b11111001010010011100000111 +
b11111001010010011100000111 3
#160
0#
#165
b11111001010010011100000111 "
b11111001010010011100000111 4
1#
#166
b10001111001010100111001000011110 +
b10001111001010100111001000011110 3
b1011 *
b1011 2
b10001111001010100111001000011110 7
b1011 6
b111100111111101111010101111001 %
b10001111001010100111001000011110 &
b1011 $
b10111100111111101111001001000100 .
b1001 /
b1000 -
1)
#170
0#
#175
1#
#176
0)
#177
b10001111001010100111001000011110 "
b10001111001010100111001000011110 4
b1011 '
b1011 0
#178
1)
b111100111111101111010101111001 +
b111100111111101111010101111001 3
#180
0#
#185
b111100111111101111010101111001 "
b111100111111101111010101111001 4
1#
#186
b11111111111000010011010011111111 +
b11111111111000010011010011111111 3
b11001 *
b11001 2
b11111111111000010011010011111111 7
b11001 6
b10001001100110101010010000010011 %
b11111111111000010011010011111111 &
b11001 $
b1001100110101010001010001011 .
b1010 /
b1001 -
1)
#190
0#
#195
1#
#196
0)
#197
b11111111111000010011010011111111 "
b11111111111000010011010011111111 4
b11001 '
b11001 0
#198
1)
b10001001100110101010010000010011 +
b10001001100110101010010000010011 3
#200
0#
#205
b10001001100110101010010000010011 "
b10001001100110101010010000010011 4
1#
#206
b1100100011110010010101111001000 +
b1100100011110010010101111001000 3
b11011 *
b11011 2
b1100100011110010010101111001000 7
b11011 6
b11000100000111101111010010001000 %
b1100100011110010010101111001000 &
b11011 $
b1000100000111101111001010011110 .
b1011 /
b1010 -
1)
#210
0#
#215
1#
#216
0)
#217
b1100100011110010010101111001000 "
b1100100011110010010101111001000 4
b11011 '
b11011 0
#218
1)
b11000100000111101111010010001000 +
b11000100000111101111010010001000 3
#220
0#
#225
b11000100000111101111010010001000 "
b11000100000111101111010010001000 4
1#
#226
b1011011000110101011111110110110 +
b1011011000110101011111110110110 3
b11 *
b11 2
b1011011000110101011111110110110 7
b11 6
b1101000111111101110100011010 %
b1011011000110101011111110110110 &
b11 $
b10001101000111111101101101101101 .
b1100 /
b1011 -
1)
#230
0#
#235
1#
#236
0)
#237
b1011011000110101011111110110110 "
b1011011000110101011111110110110 4
b11 '
b11 0
#238
1)
b1101000111111101110100011010 +
b1101000111111101110100011010 3
#240
0#
#245
b1101000111111101110100011010 "
b1101000111111101110100011010 4
1#
#246
b100010101101110111001101000101 +
b100010101101110111001101000101 3
b11000 *
b11000 2
b100010101101110111001101000101 7
b11000 6
b10001101110110110100111000011011 %
b100010101101110111001101000101 &
b11000 $
b1101110110110100110010101000 .
b1101 /
b1100 -
1)
#250
0#
#255
1#
#256
0)
#257
b100010101101110111001101000101 "
b100010101101110111001101000101 4
b11000 '
b11000 0
#258
1)
b10001101110110110100111000011011 +
b10001101110110110100111000011011 3
#260
0#
#265
b10001101110110110100111000011011 "
b10001101110110110100111000011011 4
1#
#266
b10000111001101011100011000001110 +
b10000111001101011100011000001110 3
b10000 *
b10000 2
b10000111001101011100011000001110 7
b10000 6
b11000101110000011100010010001011 %
b10000111001101011100011000001110 &
b10000 $
b1000101110000011100001110111111 .
b1110 /
b1101 -
1)
#270
0#
#275
1#
#276
0)
#277
b10000111001101011100011000001110 "
b10000111001101011100011000001110 4
b10000 '
b10000 0
#278
1)
b11000101110000011100010010001011 +
b11000101110000011100010010001011 3
#280
0#
#285
b11000101110000011100010010001011 "
b11000101110000011100010010001011 4
1#
#286
b101001111010110111001101010011 +
b101001111010110111001101010011 3
b1101 *
b1101 2
b101001111010110111001101010011 7
b1101 6
b11110111101100001111000011101111 %
b101001111010110111001101010011 &
b1101 $
b1110111101100001110111011100010 .
b1111 /
b1110 -
1)
#290
0#
#295
1#
#296
0)
#297
b101001111010110111001101010011 "
b101001111010110111001101010011 4
b1101 '
b1101 0
#298
1)
b11110111101100001111000011101111 +
b11110111101100001111000011101111 3
#300
0#
#305
b11110111101100001111000011101111 "
b11110111101100001111000011101111 4
1#
#306
b1111001000110111111100011110 +
b1111001000110111111100011110 3
b111 *
b111 2
b1111001000110111111100011110 7
b111 6
b1101000101101100100111111010001 %
b1111001000110111111100011110 &
b111 $
b11101000101101100100110000000001 .
b10000 /
b1111 -
1)
#310
0#
#315
1#
#316
0)
#317
b1111001000110111111100011110 "
b1111001000110111111100011110 4
b111 '
b111 0
#318
1)
b1101000101101100100111111010001 +
b1101000101101100100111111010001 3
#320
0#
#325
b1101000101101100100111111010001 "
b1101000101101100100111111010001 4
1#
#326
b1000100100111011000100010001 +
b1000100100111011000100010001 3
b1111 *
b1111 2
b1000100100111011000100010001 7
b1111 6
b1110001010100111010100011100 %
b1000100100111011000100010001 &
b1111 $
b10001110001010100111001111001100 .
b10001 /
b10000 -
1)
#330
0#
#335
1#
#336
0)
#337
b1000100100111011000100010001 "
b1000100100111011000100010001 4
b1111 '
b1111 0
#338
1)
b1110001010100111010100011100 +
b1110001010100111010100011100 3
#340
0#
#345
b1110001010100111010100011100 "
b1110001010100111010100011100 4
1#
#346
b11110100010011011010001011101000 +
b11110100010011011010001011101000 3
b111 *
b111 2
b11110100010011011010001011101000 7
b111 6
b110100110101111000001101101001 %
b11110100010011011010001011101000 &
b111 $
b10110100110101111000000010110011 .
b10010 /
b10001 -
1)
#350
0#
#355
1#
#356
0)
#357
b11110100010011011010001011101000 "
b11110100010011011010001011101000 4
b111 '
b111 0
#358
1)
b110100110101111000001101101001 +
b110100110101111000001101101001 3
#360
0#
#365
b110100110101111000001101101001 "
b110100110101111000001101101001 4
1#
#366
b10011101010111110010111000111010 +
b10011101010111110010111000111010 3
b101 *
b101 2
b10011101010111110010111000111010 7
b101 6
b110111100011100001100001101 %
b10011101010111110010111000111010 &
b101 $
b10000110111100011100000111100110 .
b10011 /
b10010 -
1)
#370
0#
#375
1#
#376
0)
#377
b10011101010111110010111000111010 "
b10011101010111110010111000111010 4
b101 '
b101 0
#378
1)
b110111100011100001100001101 +
b110111100011100001100001101 3
#380
0#
#385
b110111100011100001100001101 "
b110111100011100001100001101 4
1#
#386
b1011011001010010010000110110110 +
b1011011001010010010000110110110 3
b10000 *
b10000 2
b1011011001010010010000110110110 7
b10000 6
b110110001011011010110101101100 %
b1011011001010010010000110110110 &
b10000 $
b10110110001011011010101001010101 .
b10100 /
b10011 -
1)
#390
0#
#395
1#
#396
0)
#397
b1011011001010010010000110110110 "
b1011011001010010010000110110110 4
b10000 '
b10000 0
#398
1)
b110110001011011010110101101100 +
b110110001011011010110101101100 3
#400
0#
#405
b110110001011011010110101101100 "
b110110001011011010110101101100 4
1#
#406
b10010011000011001000010000100110 +
b10010011000011001000010000100110 3
b11101 *
b11101 2
b10010011000011001000010000100110 7
b11101 6
b11100111000111001010110011001110 %
b10010011000011001000010000100110 &
b11101 $
b1100111000111001010101110110000 .
b10101 /
b10100 -
1)
#410
0#
#415
1#
#416
0)
#417
b10010011000011001000010000100110 "
b10010011000011001000010000100110 4
b11101 '
b11101 0
#418
1)
b11100111000111001010110011001110 +
b11100111000111001010110011001110 3
#420
0#
#425
b11100111000111001010110011001110 "
b11100111000111001010110011001110 4
1#
#426
b1111111001110111010111111111110 +
b1111111001110111010111111111110 3
b100 *
b100 2
b1111111001110111010111111111110 7
b100 6
b10010111100100000110111000101111 %
b1111111001110111010111111111110 &
b100 $
b10111100100000110110101100111 .
b10110 /
b10101 -
1)
#430
0#
#435
1#
#436
0)
#437
b1111111001110111010111111111110 "
b1111111001110111010111111111110 4
b100 '
b100 0
#438
1)
b10010111100100000110111000101111 +
b10010111100100000110111000101111 3
#440
0#
#445
b10010111100100000110111000101111 "
b10010111100100000110111000101111 4
1#
#446
b10110111111110000000111001101111 +
b10110111111110000000111001101111 3
b11 *
b11 2
b10110111111110000000111001101111 7
b11 6
b11110111100111001001000011101111 %
b10110111111110000000111001101111 &
b11 $
b1110111100111001000111110101010 .
b10111 /
b10110 -
1)
#450
0#
#455
1#
#456
0)
#457
b10110111111110000000111001101111 "
b10110111111110000000111001101111 4
b11 '
b11 0
#458
1)
b11110111100111001001000011101111 +
b11110111100111001001000011101111 3
#460
0#
#465
b11110111100111001001000011101111 "
b11110111100111001001000011101111 4
1#
#466
b11001100101111000110111010011001 +
b11001100101111000110111010011001 3
b10110 *
b10110 2
b11001100101111000110111010011001 7
b10110 6
b11110000011001101110110011100000 %
b11001100101111000110111010011001 &
b10110 $
b1110000011001101110101001101001 .
b11000 /
b10111 -
1)
#470
0#
#475
1#
#476
0)
#477
b11001100101111000110111010011001 "
b11001100101111000110111010011001 4
b10110 '
b10110 0
#478
1)
b11110000011001101110110011100000 +
b11110000011001101110110011100000 3
#480
0#
#485
b11110000011001101110110011100000 "
b11110000011001101110110011100000 4
1#
#486
b101000010000000100000001 +
b101000010000000100000001 3
b1101 *
b1101 2
b101000010000000100000001 7
b1101 6
b10101100011110001111101001011000 %
b101000010000000100000001 &
b1101 $
b101100011110001111100001010100 .
b11001 /
b11000 -
1)
#490
0#
#495
1#
#496
0)
#497
b101000010000000100000001 "
b101000010000000100000001 4
b1101 '
b1101 0
#498
1)
b10101100011110001111101001011000 +
b10101100011110001111101001011000 3
#500
0#
#505
b10101100011110001111101001011000 "
b10101100011110001111101001011000 4
1#
#506
b11101110101101111000110011011101 +
b11101110101101111000110011011101 3
b10011 *
b10011 2
b11101110101101111000110011011101 7
b10011 6
b110010011101101111100001100 %
b11101110101101111000110011011101 &
b10011 $
b10000110010011101101110111011011 .
b11010 /
b11001 -
1)
#510
0#
#515
1#
#516
0)
#517
b11101110101101111000110011011101 "
b11101110101101111000110011011101 4
b10011 '
b10011 0
#518
1)
b110010011101101111100001100 +
b110010011101101111100001100 3
#520
0#
#525
b110010011101101111100001100 "
b110010011101101111100001100 4
1#
#526
b10010100001011011000100000101000 +
b10010100001011011000100000101000 3
b11000 *
b11000 2
b10010100001011011000100000101000 7
b11000 6
b10000000001111010011111000000000 %
b10010100001011011000100000101000 &
b11000 $
b1111010011110000101110 .
b11011 /
b11010 -
1)
#530
0#
#535
1#
#536
0)
#537
b10010100001011011000100000101000 "
b10010100001011011000100000101000 4
b11000 '
b11000 0
#538
1)
b10000000001111010011111000000000 +
b10000000001111010011111000000000 3
#540
0#
#545
b10000000001111010011111000000000 "
b10000000001111010011111000000000 4
1#
#546
b1111011010111001110011111110110 +
b1111011010111001110011111110110 3
b10010 *
b10010 2
b1111011010111001110011111110110 7
b10010 6
b1100110001100101100001111001100 %
b1111011010111001110011111110110 &
b10010 $
b11100110001100101100000000111101 .
b11100 /
b11011 -
1)
#550
0#
#555
1#
#556
0)
#557
b1111011010111001110011111110110 "
b1111011010111001110011111110110 4
b10010 '
b10010 0
#558
1)
b1100110001100101100001111001100 +
b1100110001100101100001111001100 3
#560
0#
#565
b1100110001100101100001111001100 "
b1100110001100101100001111001100 4
1#
#566
b10000011101101011111011000000111 +
b10000011101101011111011000000111 3
b10101 *
b10101 2
b10000011101101011111011000000111 7
b10101 6
b10101011110000010001111001010111 %
b10000011101101011111011000000111 &
b10101 $
b101011110000010001110110111000 .
b11101 /
b11100 -
1)
#570
0#
#575
1#
#576
0)
#577
b10000011101101011111011000000111 "
b10000011101101011111011000000111 4
b10101 '
b10101 0
#578
1)
b10101011110000010001111001010111 +
b10101011110000010001111001010111 3
#580
0#
#585
b10101011110000010001111001010111 "
b10101011110000010001111001010111 4
1#
#586
b11011100111000011010001010111001 +
b11011100111000011010001010111001 3
b1011 *
b1011 2
b11011100111000011010001010111001 7
b1011 6
b11110110000101101110100011101100 %
b11011100111000011010001010111001 &
b1011 $
b1110110000101101110011000001111 .
b11110 /
b11101 -
1)
#590
0#
#595
1#
#596
0)
#597
b11011100111000011010001010111001 "
b11011100111000011010001010111001 4
b1011 '
b1011 0
#598
1)
b11110110000101101110100011101100 +
b11110110000101101110100011101100 3
#600
0#
#605
b11110110000101101110100011101100 "
b11110110000101101110100011101100 4
1#
#606
b10110000110111101101001001100001 +
b10110000110111101101001001100001 3
b1 *
b1 2
b10110000110111101101001001100001 7
b1 6
b11000011001101000110110010000110 %
b10110000110111101101001001100001 &
b1 $
b1000011001101000110101101110010 .
b11111 /
b11110 -
1)
#610
0#
#615
1#
#616
0)
#617
b10110000110111101101001001100001 "
b10110000110111101101001001100001 4
b1 '
b1 0
#618
1)
b11000011001101000110110010000110 +
b11000011001101000110110010000110 3
#620
0#
#625
b11000011001101000110110010000110 "
b11000011001101000110110010000110 4
1#
#626
b11010100000111001101000010101000 +
b11010100000111001101000010101000 3
b1011 *
b1011 2
b11010100000111001101000010101000 7
b1011 6
b100000101001011010000101000001 %
b11010100000111001101000010101000 &
b1011 $
b10100000101001011001111111010001 .
b100000 /
b11111 -
1)
#630
0#
#635
1#
#636
0)
#637
b11010100000111001101000010101000 "
b11010100000111001101000010101000 4
b1011 '
b1011 0
#638
1)
b100000101001011010000101000001 +
b100000101001011010000101000001 3
#640
0#
#645
b100000101001011010000101000001 "
b100000101001011010000101000001 4
1#
#646
b1011110000010011111111110111100 +
b1011110000010011111111110111100 3
b11011 *
b11011 2
b1011110000010011111111110111100 7
b11011 6
b11001100000101011010000010011000 %
b1011110000010011111111110111100 &
b11011 $
b1001100000101011001111111011100 .
b100001 /
b100000 -
1)
#650
0#
#655
1#
#656
0)
#657
b1011110000010011111111110111100 "
b1011110000010011111111110111100 4
b11011 '
b11011 0
#658
1)
b11001100000101011010000010011000 +
b11001100000101011010000010011000 3
#660
0#
#665
b11001100000101011010000010011000 "
b11001100000101011010000010011000 4
1#
#666
b10101010110001110001001001010101 +
b10101010110001110001001001010101 3
b1100 *
b1100 2
b10101010110001110001001001010101 7
b1100 6
b11101101010000100101110011011010 %
b10101010110001110001001001010101 &
b1100 $
b1101101010000100101101000000011 .
b100010 /
b100001 -
1)
#670
0#
#675
1#
#676
0)
#677
b10101010110001110001001001010101 "
b10101010110001110001001001010101 4
b1100 '
b1100 0
#678
1)
b11101101010000100101110011011010 +
b11101101010000100101110011011010 3
#680
0#
#685
b11101101010000100101110011011010 "
b11101101010000100101110011011010 4
1#
#686
b11011010001001101101110010110100 +
b11011010001001101101110010110100 3
b1101 *
b1101 2
b11011010001001101101110010110100 7
b1101 6
b10000100011110111000001000001000 %
b11011010001001101101110010110100 &
b1101 $
b100011110111000000101110110 .
b100011 /
b100010 -
1)
#690
0#
#695
1#
#696
0)
#697
b11011010001001101101110010110100 "
b11011010001001101101110010110100 4
b1101 '
b1101 0
#698
1)
b10000100011110111000001000001000 +
b10000100011110111000001000001000 3
#700
0#
#705
b10000100011110111000001000001000 "
b10000100011110111000001000001000 4
1#
#706
b10001110000001010010111000011100 +
b10001110000001010010111000011100 3
b11011 *
b11011 2
b10001110000001010010111000011100 7
b11011 6
b101011001010111011111101010110 %
b10001110000001010010111000011100 &
b11011 $
b10101011001010111011110100100101 .
b100100 /
b100011 -
1)
#710
0#
#715
1#
#716
0)
#717
b10001110000001010010111000011100 "
b10001110000001010010111000011100 4
b11011 '
b11011 0
#718
1)
b101011001010111011111101010110 +
b101011001010111011111101010110 3
#720
0#
#725
b101011001010111011111101010110 "
b101011001010111011111101010110 4
1#
#726
b100011111010010110100101000111 +
b100011111010010110100101000111 3
b1111 *
b1111 2
b100011111010010110100101000111 7
b1111 6
b10110110011100010100000101 %
b100011111010010110100101000111 &
b1111 $
b10000010110110011100001011000000 .
b100101 /
b100100 -
1)
#730
0#
#735
1#
#736
0)
#737
b100011111010010110100101000111 "
b100011111010010110100101000111 4
b1111 '
b1111 0
#738
1)
b10110110011100010100000101 +
b10110110011100010100000101 3
#740
0#
#745
b10110110011100010100000101 "
b10110110011100010100000101 4
1#
#746
b11000110101001011100000010001101 +
b11000110101001011100000010001101 3
b10100 *
b10100 2
b11000110101001011100000010001101 7
b10100 6
b111011111101001100111101110111 %
b11000110101001011100000010001101 &
b10100 $
b10111011111101001100110110110111 .
b100110 /
b100101 -
1)
#750
0#
#755
1#
#756
0)
#757
b11000110101001011100000010001101 "
b11000110101001011100000010001101 4
b10100 '
b10100 0
#758
1)
b111011111101001100111101110111 +
b111011111101001100111101110111 3
#760
0#
#765
b111011111101001100111101110111 "
b111011111101001100111101110111 4
1#
#766
b101011111100000101110101010111 +
b101011111100000101110101010111 3
b11110 *
b11110 2
b101011111100000101110101010111 7
b11110 6
b10111110001010001010010001111100 %
b101011111100000101110101010111 &
b11110 $
b111110001010001010001000111010 .
b100111 /
b100110 -
1)
#770
0#
#775
1#
#776
0)
#777
b101011111100000101110101010111 "
b101011111100000101110101010111 4
b11110 '
b11110 0
#778
1)
b10111110001010001010010001111100 +
b10111110001010001010010001111100 3
#780
0#
#785
b10111110001010001010010001111100 "
b10111110001010001010010001111100 4
1#
#786
b1001011001110011100011110010110 +
b1001011001110011100011110010110 3
b10010 *
b10010 2
b1001011001110011100011110010110 7
b10010 6
b11110001010111010000111011100010 %
b1001011001110011100011110010110 &
b10010 $
b1110001010111010000110000111001 .
b101000 /
b100111 -
1)
#790
0#
#795
1#
#796
0)
#797
b1001011001110011100011110010110 "
b1001011001110011100011110010110 4
b10010 '
b10010 0
#798
1)
b11110001010111010000111011100010 +
b11110001010111010000111011100010 3
#800
0#
#805
b11110001010111010000111011100010 "
b11110001010111010000111011100010 4
1#
#806
b11111011001000100100101011110110 +
b11111011001000100100101011110110 3
b11010 *
b11010 2
b11111011001000100100101011110110 7
b11010 6
b100001000101111000110101000010 %
b11111011001000100100101011110110 &
b11010 $
b10100001000101111000101001100100 .
b101001 /
b101000 -
1)
#810
0#
#815
1#
#816
0)
#817
b11111011001000100100101011110110 "
b11111011001000100100101011110110 4
b11010 '
b11010 0
#818
1)
b100001000101111000110101000010 +
b100001000101111000110101000010 3
#820
0#
#825
b100001000101111000110101000010 "
b100001000101111000110101000010 4
1#
#826
b10101000111100000101000001010001 +
b10101000111100000101000001010001 3
b11000 *
b11000 2
b10101000111100000101000001010001 7
b11000 6
b11001100010011111001011010011000 %
b10101000111100000101000001010001 &
b11000 $
b1001100010011111001010100101011 .
b101010 /
b101001 -
1)
#830
0#
#835
1#
#836
0)
#837
b10101000111100000101000001010001 "
b10101000111100000101000001010001 4
b11000 '
b11000 0
#838
1)
b11001100010011111001011010011000 +
b11001100010011111001011010011000 3
#840
0#
#845
b11001100010011111001011010011000 "
b11001100010011111001011010011000 4
1#
#846
b1100010010010011100010111000100 +
b1100010010010011100010111000100 3
b10110 *
b10110 2
b1100010010010011100010111000100 7
b10110 6
b110111101100101011001101101111 %
b1100010010010011100010111000100 &
b10110 $
b10110111101100101011000110111110 .
b101011 /
b101010 -
1)
#850
0#
#855
1#
#856
0)
#857
b1100010010010011100010111000100 "
b1100010010010011100010111000100 4
b10110 '
b10110 0
#858
1)
b110111101100101011001101101111 +
b110111101100101011001101101111 3
#860
0#
#865
b110111101100101011001101101111 "
b110111101100101011001101101111 4
1#
#866
b101010110111010001101101010101 +
b101010110111010001101101010101 3
b11101 *
b11101 2
b101010110111010001101101010101 7
b11101 6
b10100110100100010100001001001101 %
b101010110111010001101101010101 &
b11101 $
b100110100100010100000100001101 .
b101100 /
b101011 -
1)
#870
0#
#875
1#
#876
0)
#877
b101010110111010001101101010101 "
b101010110111010001101101010101 4
b11101 '
b11101 0
#878
1)
b10100110100100010100001001001101 +
b10100110100100010100001001001101 3
#880
0#
#885
b10100110100100010100001001001101 "
b10100110100100010100001001001101 4
1#
#886
b1101001101110000111100111010011 +
b1101001101110000111100111010011 3
b111 *
b111 2
b1101001101110000111100111010011 7
b111 6
b1111101101000111011110111111011 %
b1101001101110000111100111010011 &
b111 $
b11111101101000111011101011001000 .
b101101 /
b101100 -
1)
#890
0#
#895
1#
#896
0)
#897
b1101001101110000111100111010011 "
b1101001101110000111100111010011 4
b111 '
b111 0
#898
1)
b1111101101000111011110111111011 +
b1111101101000111011110111111011 3
#900
0#
#905
b1111101101000111011110111111011 "
b1111101101000111011110111111011 4
1#
#906
b10101100000100100010100001011000 +
b10101100000100100010100001011000 3
b1110 *
b1110 2
b10101100000100100010100001011000 7
b1110 6
b11011110011001011100011010111100 %
b10101100000100100010100001011000 &
b1110 $
b1011110011001011100010001011111 .
b101110 /
b101101 -
1)
#910
0#
#915
1#
#916
0)
#917
b10101100000100100010100001011000 "
b10101100000100100010100001011000 4
b1110 '
b1110 0
#918
1)
b11011110011001011100011010111100 +
b11011110011001011100011010111100 3
#920
0#
#925
b11011110011001011100011010111100 "
b11011110011001011100011010111100 4
1#
#926
b1101011011110010100110111010110 +
b1101011011110010100110111010110 3
b1101 *
b1101 2
b1101011011110010100110111010110 7
b1101 6
b10000011111101010101011000000111 %
b1101011011110010100110111010110 &
b1101 $
b11111101010101010000000010 .
b101111 /
b101110 -
1)
#930
0#
#935
1#
